LICENSE.txt
README.md
setup.py
hierarchical_ensemble_classifier/__init__.py
hierarchical_ensemble_classifier/hierarchical_ensemble_classifier.py
hierarchical_ensemble_classifier.egg-info/PKG-INFO
hierarchical_ensemble_classifier.egg-info/SOURCES.txt
hierarchical_ensemble_classifier.egg-info/dependency_links.txt
hierarchical_ensemble_classifier.egg-info/requires.txt
hierarchical_ensemble_classifier.egg-info/top_level.txt